dep_client/__init__.py
dep_client/__main__.py
dep_client/args/Args.py
dep_client/args/__init__.py
dep_client/client/Client.py
dep_client/client/__init__.py
dep_client/output/Output.py
dep_client/output/__init__.py
dep_client/util/Util.py
dep_client/util/__init__.py
dep_client-1.0.1.dist-info/METADATA
dep_client-1.0.1.dist-info/WHEEL
dep_client-1.0.1.dist-info/entry_points.txt
dep_client-1.0.1.dist-info/top_level.txt
dep_client-1.0.1.dist-info/RECORD
