Metadata-Version: 2.1
Name: dep_client
Version: 1.0.1
Summary: Data Exfiltration Protocol (DEP) Client - Transfer data with DEP
Home-page: https://github.com/npdep/dep-client
Author: npdep
Classifier: Operating System :: OS Independent 
Classifier: Programming Language :: Python :: 3 
Requires-Dist: dep-common
